miu_code/__init__.py
miu_code/__main__.py
miu_code/acp/__init__.py
miu_code/acp/server.py
miu_code/agent/__init__.py
miu_code/agent/coding.py
miu_code/cli/__init__.py
miu_code/cli/entry.py
miu_code/commands/__init__.py
miu_code/commands/commit.md
miu_code/commands/cook.md
miu_code/commands/plan.md
miu_code/session/__init__.py
miu_code/session/storage.py
miu_code/tools/__init__.py
miu_code/tools/bash.py
miu_code/tools/edit.py
miu_code/tools/glob.py
miu_code/tools/grep.py
miu_code/tools/read.py
miu_code/tools/security.py
miu_code/tools/write.py
miu_code/tui/__init__.py
miu_code/tui/app.py
miu_code/tui/app.tcss
miu_code/tui/theme.py
miu_code/tui/widgets/__init__.py
miu_code/tui/widgets/approval.py
miu_code/tui/widgets/banner.py
miu_code/tui/widgets/chat.py
miu_code/tui/widgets/input.py
miu_code/tui/widgets/loading.py
miu_code/tui/widgets/messages.py
miu_code/tui/widgets/spinner.py
miu_code/tui/widgets/status.py
miu_code/tui/widgets/tools.py
miu_code/tui/widgets/chat_input/__init__.py
miu_code/tui/widgets/chat_input/body.py
miu_code/tui/widgets/chat_input/completion_popup.py
miu_code/tui/widgets/chat_input/container.py
miu_code/tui/widgets/chat_input/history.py
miu_code/tui/widgets/chat_input/text_area.py
miu_code-1.0.0.dist-info/METADATA
miu_code-1.0.0.dist-info/WHEEL
miu_code-1.0.0.dist-info/entry_points.txt
miu_code-1.0.0.dist-info/RECORD
